ll_kugou_lyric_api/__init__.py
ll_kugou_lyric_api/core.py
ll_kugou_lyric_api-0.1.4.dist-info/licenses/LICENSE
ll_kugou_lyric_api-0.1.4.dist-info/WHEEL
ll_kugou_lyric_api-0.1.4.dist-info/METADATA
ll_kugou_lyric_api-0.1.4.dist-info/RECORD
