Metadata-Version: 2.4
Name: ll_kugou_lyric_api
Version: 0.1.4
Summary: A simple Kugou lyrics fetcher
Author-email: 刘龙 <1053278842@qq.com>
Requires-Python: >=3.7
License-File: LICENSE
Requires-Dist: requests
